README.md
setup.py
BestArbitrage/__init__.py
BestArbitrage/core.py
BestArbitrage.egg-info/PKG-INFO
BestArbitrage.egg-info/SOURCES.txt
BestArbitrage.egg-info/dependency_links.txt
BestArbitrage.egg-info/requires.txt
BestArbitrage.egg-info/top_level.txt
BestArbitrage/inter_exchange/__init__.py
BestArbitrage/inter_exchange/bestexchange.py
BestArbitrage/inter_exchange/trader_bot.py
BestArbitrage/inter_exchange/tradeview_find.py
BestArbitrage/intra_exchange/__init__.py
BestArbitrage/intra_exchange/bestchain.py
BestArbitrage/intra_exchange/parser.py
BestArbitrage/intra_exchange/trader_bot.py