Metadata-Version: 2.1
Name: BestArbitrage
Version: 0.4.0
Summary: Arbitrage cryptocurrency smartly
Home-page: https://github.com/VladKochetov007/BestArbitrage
Author: Vlad Kochetov
Author-email: vladyslavdrrragonkoch@gmail.com
License: UNKNOWN
Download-URL: https://github.com/VladKochetov007/BestArbitrage/archive/0.4.0.tar.gz
Platform: UNKNOWN
